FlowViewer/__init__.py
FlowViewer/base.py
FlowViewer/base.pyi
FlowViewer/listener.py
FlowViewer/listener.pyi
FlowViewer/request_man.py
FlowViewer/request_man.pyi
FlowViewer-0.3.0.dist-info/LICENSE
FlowViewer-0.3.0.dist-info/METADATA
FlowViewer-0.3.0.dist-info/WHEEL
FlowViewer-0.3.0.dist-info/top_level.txt
FlowViewer-0.3.0.dist-info/RECORD
